planet_generator/__init__.py
planet_generator/_version.py
planet_generator/client.py
planet_generator/config.py
planet_generator/primitives.py
planet_generator/protocol.py
planet_generator/sprite.py
planet_generator_sdk-0.1.2.dist-info/METADATA
planet_generator_sdk-0.1.2.dist-info/WHEEL
planet_generator_sdk-0.1.2.dist-info/top_level.txt
planet_generator_sdk-0.1.2.dist-info/RECORD
