Metadata-Version: 2.1
Name: planet-generator-sdk
Version: 0.1.2
Summary: Python SDk for Planet API, the 2D planet sprite generator.
Home-page: https://planet.joffreybvn.be
Author: Joffrey Bienvenu
Author-email: joffreybvn@gmail.com
License: MIT
Project-URL: Documentation, https://planet.joffreybvn.be/python-sdk/index.html
Project-URL: Source, https://github.com/planet-api/python-sdk
Project-URL: Tracker, https://github.com/planet-api/python-sdk/issues
Project-URL: Community, https://discord.gg/SEGApgznjq
Classifier: Intended Audience :: Developers
Classifier: License :: OSI Approved :: MIT License
Classifier: Programming Language :: Python
Classifier: Programming Language :: Python :: 3
Classifier: Programming Language :: Python :: 3.7
Classifier: Programming Language :: Python :: 3.8
Classifier: Programming Language :: Python :: 3.9
Classifier: Programming Language :: Python :: 3.10
Classifier: Operating System :: OS Independent
Requires-Dist: Pillow
